TasKKontrol/Kontroller.py
TasKKontrol/Task.py
TasKKontrol/Triggers.py
TasKKontrol/Utils.py
TasKKontrol-0.1.0a0.dist-info/LICENSE.txt
TasKKontrol-0.1.0a0.dist-info/METADATA
TasKKontrol-0.1.0a0.dist-info/WHEEL
TasKKontrol-0.1.0a0.dist-info/top_level.txt
TasKKontrol-0.1.0a0.dist-info/RECORD
