Metadata-Version: 2.2
Name: TasKKontrol
Version: 0.1.0a0
Summary: Task automation library
Home-page: https://github.com/Rkaid0/TasKKontrol
Author: Artyom Yesayan
Author-email: yesart8@gmail.com
License: MIT
Keywords: Workflow,Automation,Task
Classifier: Intended Audience :: Developers
Classifier: License :: OSI Approved :: MIT License
Classifier: Programming Language :: Python :: 3
License-File: LICENSE.txt
Dynamic: author
Dynamic: author-email
Dynamic: classifier
Dynamic: description
Dynamic: description-content-type
Dynamic: home-page
Dynamic: keywords
Dynamic: license
Dynamic: summary
